examples/__init__.py
examples/urls.py
examples/views.py
examples/templates/404.html
examples/templates/500.html
examples/templates/base.html
setup/__init__.py
setup/urls.py
setup/wsgi.py
setup/settings/__init__.py
setup/settings/base.py
setup/settings/dev.py
snotra_rss/__init__.py
snotra_rss/apps.py
snotra_rss/models.py
snotra_rss/urls.py
snotra_rss/wagtail_hooks.py
snotra_rss/migrations/__init__.py
snotra_rss-0.2.5.6.dist-info/LICENSE
snotra_rss-0.2.5.6.dist-info/METADATA
snotra_rss-0.2.5.6.dist-info/WHEEL
snotra_rss-0.2.5.6.dist-info/top_level.txt
snotra_rss-0.2.5.6.dist-info/RECORD
