Metadata-Version: 2.1
Name: snotra-rss
Version: 0.2.5.6
Summary: Wagtail app - with rss aggregator and tweeter aggregator feature
Home-page: https://github.com/olopost/snotra_rss
Author: Samuel MEYNARD
Author-email: samuel@meyn.fr
License: UNKNOWN
Platform: UNKNOWN
Classifier: Programming Language :: Python :: 3
Classifier: Programming Language :: Python :: 3.4
Classifier: Programming Language :: Python :: 3.6
Classifier: Programming Language :: Python :: 3.6
Classifier: Programming Language :: Python :: 3.7
Classifier: Programming Language :: Python :: 3.8
Classifier: Framework :: Django :: 3.0
Classifier: Framework :: Django :: 3.1
Classifier: Framework :: Wagtail
Classifier: Framework :: Wagtail :: 2
Classifier: License :: OSI Approved :: BSD License
Classifier: Operating System :: OS Independent
Classifier: Development Status :: 4 - Beta
Requires-Dist: Django (>=2.1)
Requires-Dist: wagtail (>=2.4)
Requires-Dist: feedparser
Requires-Dist: pygelf4ovh
Requires-Dist: python-twitter
Requires-Dist: twine
Requires-Dist: setuptools
